kuda_cli/__init__.py
kuda_cli/accounts.py
kuda_cli/billing_and_betting.py
kuda_cli/card.py
kuda_cli/gift_card.py
kuda_cli/main.py
kuda_cli/savings.py
kuda_cli/transaction.py
kuda_cli/utils.py
kuda_cli-0.1.0.dist-info/METADATA
kuda_cli-0.1.0.dist-info/WHEEL
kuda_cli-0.1.0.dist-info/entry_points.txt
kuda_cli-0.1.0.dist-info/RECORD
