Metadata-Version: 2.1
Name: kuda-cli
Version: 0.1.0
Summary: 
Author: Gbenga Adeyi
Author-email: adeyigbenga005@gmail.com
Requires-Python: >=3.9,<3.13
Classifier: Programming Language :: Python :: 3
Classifier: Programming Language :: Python :: 3.9
Classifier: Programming Language :: Python :: 3.10
Classifier: Programming Language :: Python :: 3.11
Requires-Dist: pykuda2 (>=0.1.2,<0.2.0)
Requires-Dist: typer[all] (>=0.9.0,<0.10.0)
